{"frames":{"doodlejump1":{"frame":{"x":0,"y":0,"w":109,"h":158},"rotated":false,"trimmed":false,"spriteSourceSize":{"x":0,"y":0,"w":109,"h":158},"sourceSize":{"w":109,"h":158}},"doodlejump2":{"frame":{"x":110,"y":0,"w":109,"h":158},"rotated":false,"trimmed":false,"spriteSourceSize":{"x":0,"y":0,"w":109,"h":158},"sourceSize":{"w":109,"h":158}},"doodlejump3":{"frame":{"x":0,"y":159,"w":109,"h":158},"rotated":false,"trimmed":false,"spriteSourceSize":{"x":0,"y":0,"w":109,"h":158},"sourceSize":{"w":109,"h":158}},"doodlejump4":{"frame":{"x":110,"y":159,"w":109,"h":158},"rotated":false,"trimmed":false,"spriteSourceSize":{"x":0,"y":0,"w":109,"h":158},"sourceSize":{"w":109,"h":158}},"doodlejump5":{"frame":{"x":220,"y":0,"w":109,"h":158},"rotated":false,"trimmed":false,"spriteSourceSize":{"x":0,"y":0,"w":109,"h":158},"sourceSize":{"w":109,"h":158}},"doodlejump6":{"frame":{"x":220,"y":159,"w":109,"h":158},"rotated":false,"trimmed":false,"spriteSourceSize":{"x":0,"y":0,"w":109,"h":158},"sourceSize":{"w":109,"h":158}},"doodlejump7":{"frame":{"x":330,"y":0,"w":109,"h":158},"rotated":false,"trimmed":false,"spriteSourceSize":{"x":0,"y":0,"w":109,"h":158},"sourceSize":{"w":109,"h":158}},"doodlejump8":{"frame":{"x":330,"y":159,"w":109,"h":158},"rotated":false,"trimmed":false,"spriteSourceSize":{"x":0,"y":0,"w":109,"h":158},"sourceSize":{"w":109,"h":158}},"doodlejump9":{"frame":{"x":0,"y":318,"w":109,"h":158},"rotated":false,"trimmed":false,"spriteSourceSize":{"x":0,"y":0,"w":109,"h":158},"sourceSize":{"w":109,"h":158}},"doodlejump10":{"frame":{"x":110,"y":318,"w":109,"h":158},"rotated":false,"trimmed":false,"spriteSourceSize":{"x":0,"y":0,"w":109,"h":158},"sourceSize":{"w":109,"h":158}},"doodlejump11":{"frame":{"x":220,"y":318,"w":109,"h":158},"rotated":false,"trimmed":false,"spriteSourceSize":{"x":0,"y":0,"w":109,"h":158},"sourceSize":{"w":109,"h":158}},"doodlejump12":{"frame":{"x":330,"y":318,"w":109,"h":158},"rotated":false,"trimmed":false,"spriteSourceSize":{"x":0,"y":0,"w":109,"h":158},"sourceSize":{"w":109,"h":158}},"default":{"frame":{"x":440,"y":0,"w":109,"h":158},"rotated":false,"trimmed":false,"spriteSourceSize":{"x":0,"y":0,"w":109,"h":158},"sourceSize":{"w":109,"h":158}}},"meta":{"app":"https://www.leshylabs.com/apps/sstool/","version":"Leshy SpriteSheet Tool v0.8.4","image":"phone1_atlas.png","size":{"w":549,"h":476},"scale":1}}